{
"characters":[
 {
  "code": "006Boy",
  "group": "Normal",
  "name": "Hat Boy",
  "life": 105,
  "damage": 31,
  "ability": 53,
  "defense": 12,
  "attackSpeed": 1.4,
  "rechargeAbilitySpeed": 1.79,
  "framesRV": 2,
  "framesRH": 5,
  "framesWV": 1,
  "framesWH": 8,
  "framesIV": 2,
  "framesIH": 5
 },
 {
  "code": "007Dino",
  "group": "Rare",
  "name": "Trex",
  "life": 105,
  "damage": 32,
  "ability": 54,
  "defense": 13,
  "attackSpeed": 1.6,
  "rechargeAbilitySpeed": 1.85,
  "framesRV": 1,
  "framesRH": 8,
  "framesWV": 2,
  "framesWH": 5,
  "framesIV": 2,
  "framesIH": 5
 },
 {
  "code": "008Santa",
  "group": "Rare",
  "name": "Santa",
  "life": 110,
  "damage": 37,
  "ability": 56,
  "defense": 10,
  "attackSpeed": 1.45,
  "rechargeAbilitySpeed": 0.85,
  "framesRV": 2,
  "framesRH": 5,
  "framesWV": 2,
  "framesWH": 5,
  "framesIV": 2,
  "framesIH": 8
 },
 {
  "code": "009Cowgirl",
  "group": "Normal",
  "name": "Cowgirl",
  "life": 92,
  "damage": 38,
  "ability": 50,
  "defense": 20,
  "attackSpeed": 1.11,
  "rechargeAbilitySpeed": 0.55,
  "framesRV": 2,
  "framesRH": 5,
  "framesWV": 1,
  "framesWH": 8,
  "framesIV": 1,
  "framesIH": 9
 },
 {
  "code": "010Knight",
  "group": "Normal",
  "name": "Knight",
  "life": 94,
  "damage": 36,
  "ability": 52,
  "defense": 18,
  "attackSpeed": 1.02,
  "rechargeAbilitySpeed": 1.01,
  "framesRV": 2,
  "framesRH": 5,
  "framesWV": 2,
  "framesWH": 5,
  "framesIV": 2,
  "framesIH": 5
 },
 {
  "code": "011Jack",
  "group": "Rare",
  "name": "Jack O Lantern",
  "life": 101,
  "damage": 32,
  "ability": 73,
  "defense": 12,
  "attackSpeed": 1.54,
  "rechargeAbilitySpeed": 0.72,
  "framesRV": 1,
  "framesRH": 8,
  "framesWV": 2,
  "framesWH": 5,
  "framesIV": 2,
  "framesIH": 5
 },
 {
  "code": "012Ninja",
  "group": "Normal",
  "name": "Ninja",
  "life": 100,
  "damage": 44,
  "ability": 65,
  "defense": 18,
  "attackSpeed": 1.14,
  "rechargeAbilitySpeed": 1.12,
  "framesRV": 1,
  "framesRH": 10,
  "framesWV": 2,
  "framesWH": 5,
  "framesIV": 1,
  "framesIH": 9
 },
 {
  "code": "013NinjaGirl",
  "group": "Normal",
  "name": "Ninja Girl",
  "life": 119,
  "damage": 39,
  "ability": 55,
  "defense": 17,
  "attackSpeed": 1.27,
  "rechargeAbilitySpeed": 0.59,
  "framesRV": 1,
  "framesRH": 9,
  "framesWV": 2,
  "framesWH": 5,
  "framesIV": 2,
  "framesIH": 5
 },
 {
  "code": "014Robot",
  "group": "Rare",
  "name": "Robot",
  "life": 119,
  "damage": 40,
  "ability": 57,
  "defense": 17,
  "attackSpeed": 1.62,
  "rechargeAbilitySpeed": 0.64,
  "framesRV": 1,
  "framesRH": 9,
  "framesWV": 1,
  "framesWH": 8,
  "framesIV": 2,
  "framesIH": 5
 },
 {
  "code": "015Cowboy",
  "group": "Rare",
  "name": "Cowboy",
  "life": 83,
  "damage": 49,
  "ability": 51,
  "defense": 20,
  "attackSpeed": 1.09,
  "rechargeAbilitySpeed": 0.81,
  "framesRV": 2,
  "framesRH": 5,
  "framesWV": 2,
  "framesWH": 5,
  "framesIV": 2,
  "framesIH": 5
 },
 {
  "code": "016Zombie",
  "group": "Legendary",
  "name": "Zombie",
  "life": 118,
  "damage": 35,
  "ability": 67,
  "defense": 11,
  "attackSpeed": 0.68,
  "rechargeAbilitySpeed": 0.68,
  "framesRV": 2,
  "framesRH": 5,
  "framesWV": 2,
  "framesWH": 5,
  "framesIV": 2,
  "framesIH": 7
 },
 {
  "code": "017Zombie",
  "group": "Legendary",
  "name": "Zombie",
  "life": 104,
  "damage": 31,
  "ability": 67,
  "defense": 13,
  "attackSpeed": 1.82,
  "rechargeAbilitySpeed": 1.68,
  "framesRV": 2,
  "framesRH": 5,
  "framesWV": 2,
  "framesWH": 5,
  "framesIV": 2,
  "framesIH": 7
 },
 {
  "code": "001Axolotl",
  "group": "Mythic",
  "name": "Axolotl",
  "life": 84,
  "damage": 41,
  "ability": 55,
  "defense": 13,
  "attackSpeed": 0.52,
  "rechargeAbilitySpeed": 1.79,
  "framesRV": 1,
  "framesRH": 5,
  "framesWV": 1,
  "framesWH": 5,
  "framesIV": 1,
  "framesIH": 1
 },
 {
  "code": "002FutureKnight",
  "group": "Legendary",
  "name": "Future Knight",
  "life": 82,
  "damage": 47,
  "ability": 61,
  "defense": 14,
  "attackSpeed": 1.97,
  "rechargeAbilitySpeed": 1.53,
  "framesRV": 1,
  "framesRH": 6,
  "framesWV": 1,
  "framesWH": 6,
  "framesIV": 1,
  "framesIH": 1
 },
 {
  "code": "004OriginalNinja",
  "group": "Rare",
  "name": "Original Ninja",
  "life": 101,
  "damage": 46,
  "ability": 62,
  "defense": 13,
  "attackSpeed": 1.32,
  "rechargeAbilitySpeed": 1.99,
  "framesRV": 2,
  "framesRH": 5,
  "framesWV": 2,
  "framesWH": 5,
  "framesIV": 1,
  "framesIH": 1
 },
 {
  "code": "005HalfZombie",
  "group": "Rare",
  "name": "Half Zombie",
  "life": 116,
  "damage": 50,
  "ability": 51,
  "defense": 18,
  "attackSpeed": 1.93,
  "rechargeAbilitySpeed": 1.41,
  "framesRV": 1,
  "framesRH": 4,
  "framesWV": 1,
  "framesWH": 4,
  "framesIV": 1,
  "framesIH": 1
 }
]}